qrs32lib/__init__.py
qrs32lib/model.py
qrs32lib-0.1.0.dist-info/METADATA
qrs32lib-0.1.0.dist-info/WHEEL
qrs32lib-0.1.0.dist-info/top_level.txt
qrs32lib-0.1.0.dist-info/RECORD
